namedstruct/__init__.py
namedstruct/namedstruct.py
namedstruct/stdprim.py
nstruct-1.3.1.dist-info/LICENSE
nstruct-1.3.1.dist-info/METADATA
nstruct-1.3.1.dist-info/WHEEL
nstruct-1.3.1.dist-info/top_level.txt
nstruct-1.3.1.dist-info/RECORD
