Metadata-Version: 2.1
Name: nstruct
Version: 1.3.1
Summary: Define complicate C/C++ structs in Python to parse/pack them from/to raw bytes
Home-page: http://github.com/hubo1016/namedstruct
Author: Hu Bo
Author-email: hubo1016@126.com
License: http://www.apache.org/licenses/LICENSE-2.0
Keywords: Openflow,struct,parse,protocol
Platform: UNKNOWN
